mbufferio/__init__.py
mbufferio/_mbufferio.c
mbufferio/_mbufferio.pxd
mbufferio/_mbufferio.pyx
mbufferio/_mbufferio.so
mbufferio/murmur.c
mbufferio/murmur.h
mbufferio-0.5.8.dist-info/DESCRIPTION.rst
mbufferio-0.5.8.dist-info/METADATA
mbufferio-0.5.8.dist-info/RECORD
mbufferio-0.5.8.dist-info/WHEEL
mbufferio-0.5.8.dist-info/metadata.json
mbufferio-0.5.8.dist-info/top_level.txt
