Metadata-Version: 2.0
Name: mbufferio
Version: 0.5.8
Summary: A convenient class to manipulate buffer objects as streams in Python
Home-page: https://github.com/stephane-martin/mbufferio
Author: Stephane Martin
Author-email: stephane.martin_github@vesperal.eu
License: LGPL v3
Keywords: buffers streams io bufferprotocol
Platform: UNKNOWN
Classifier: Development Status :: 4 - Beta
Classifier: Programming Language :: C
Classifier: Programming Language :: Python :: 2.7
Classifier: Programming Language :: Python :: 3
Classifier: Programming Language :: Cython
Classifier: Operating System :: POSIX
Classifier: Topic :: Software Development :: Libraries
